mopen/__init__.py
mopen/mopen.py
mopen-1.dist-info/LICENSE
mopen-1.dist-info/METADATA
mopen-1.dist-info/WHEEL
mopen-1.dist-info/entry_points.txt
mopen-1.dist-info/top_level.txt
mopen-1.dist-info/RECORD
