Metadata-Version: 2.1
Name: mopen
Version: 1
Summary: File opener using mimetypes and mailcap
Home-page: https://github.com/gokcehan/mopen
Author: Gokcehan Kara
Author-email: gokcehankara@gmail.com
License: UNKNOWN
Platform: UNKNOWN
